deutschland/tagesschau/__init__.py
deutschland/tagesschau/api/__init__.py
deutschland/tagesschau/api/channels_api.py
deutschland/tagesschau/api/homepage_api.py
deutschland/tagesschau/api/news_api.py
deutschland/tagesschau/api/search_api.py
deutschland/tagesschau/api_client.py
deutschland/tagesschau/apis/__init__.py
deutschland/tagesschau/configuration.py
deutschland/tagesschau/exceptions.py
deutschland/tagesschau/model/__init__.py
deutschland/tagesschau/model/channels_response.py
deutschland/tagesschau/model/channels_response_channels_inner.py
deutschland/tagesschau/model/homepage_response.py
deutschland/tagesschau/model/homepage_response_news_inner.py
deutschland/tagesschau/model/homepage_response_regional_inner.py
deutschland/tagesschau/model/multimedia_response.py
deutschland/tagesschau/model/news_response.py
deutschland/tagesschau/model/news_response_news_inner.py
deutschland/tagesschau/model/search_response.py
deutschland/tagesschau/model/search_response_search_results_inner.py
deutschland/tagesschau/model_utils.py
deutschland/tagesschau/models/__init__.py
deutschland/tagesschau/rest.py
de_tagesschau-0.2.0.dist-info/METADATA
de_tagesschau-0.2.0.dist-info/WHEEL
de_tagesschau-0.2.0.dist-info/RECORD
